mvn_mcp_server/__init__.py
mvn_mcp_server/main.py
mvn_mcp_server/server.py
mvn_mcp_server/prompts/__init__.py
mvn_mcp_server/prompts/list_mcp_assets.py
mvn_mcp_server/prompts/plan.py
mvn_mcp_server/prompts/triage.py
mvn_mcp_server/resources/__init__.py
mvn_mcp_server/resources/server_assets.py
mvn_mcp_server/resources/triage_reports.py
mvn_mcp_server/resources/update_plans.py
mvn_mcp_server/services/__init__.py
mvn_mcp_server/services/cache.py
mvn_mcp_server/services/maven_api.py
mvn_mcp_server/services/maven_effective_pom.py
mvn_mcp_server/services/response.py
mvn_mcp_server/services/version.py
mvn_mcp_server/shared/__init__.py
mvn_mcp_server/shared/config.py
mvn_mcp_server/shared/data_types.py
mvn_mcp_server/shared/logging.py
mvn_mcp_server/shared/utils.py
mvn_mcp_server/tests/__init__.py
mvn_mcp_server/tests/test_server_integration.py
mvn_mcp_server/tests/prompts/__init__.py
mvn_mcp_server/tests/prompts/test_list_mcp_assets.py
mvn_mcp_server/tests/prompts/test_plan.py
mvn_mcp_server/tests/prompts/test_triage.py
mvn_mcp_server/tests/resources/__init__.py
mvn_mcp_server/tests/resources/test_resources.py
mvn_mcp_server/tests/services/__init__.py
mvn_mcp_server/tests/services/test_cache.py
mvn_mcp_server/tests/services/test_maven_api.py
mvn_mcp_server/tests/services/test_maven_effective_pom.py
mvn_mcp_server/tests/services/test_version.py
mvn_mcp_server/tests/shared/__init__.py
mvn_mcp_server/tests/shared/test_utils.py
mvn_mcp_server/tests/tools/__init__.py
mvn_mcp_server/tests/tools/test_check_version.py
mvn_mcp_server/tests/tools/test_check_version_batch.py
mvn_mcp_server/tests/tools/test_java_security_scan.py
mvn_mcp_server/tests/tools/test_list_available_versions.py
mvn_mcp_server/tools/__init__.py
mvn_mcp_server/tools/analyze_pom_file.py
mvn_mcp_server/tools/check_version.py
mvn_mcp_server/tools/check_version_batch.py
mvn_mcp_server/tools/java_security_scan.py
mvn_mcp_server/tools/list_available_versions.py
mvn_mcp_server/tools/maven.py
mvn_mcp_server-2.3.0.dist-info/licenses/LICENSE
mvn_mcp_server-2.3.0.dist-info/METADATA
mvn_mcp_server-2.3.0.dist-info/WHEEL
mvn_mcp_server-2.3.0.dist-info/entry_points.txt
mvn_mcp_server-2.3.0.dist-info/top_level.txt
mvn_mcp_server-2.3.0.dist-info/RECORD
