Metadata-Version: 2.4
Name: mvn-mcp-server
Version: 2.3.0
Summary: A MCP server for Maven dependency version checking
Author: Daniel Scholl
Maintainer-email: Daniel Scholl <daniel.scholl@microsoft.com>
License: MIT
Project-URL: Homepage, https://github.com/danielscholl/mvn-mcp-server
Project-URL: Repository, https://github.com/danielscholl/mvn-mcp-server
Project-URL: Documentation, https://github.com/danielscholl/mvn-mcp-server#readme
Project-URL: Issues, https://github.com/danielscholl/mvn-mcp-server/issues
Project-URL: Changelog, https://github.com/danielscholl/mvn-mcp-server/blob/main/CHANGELOG.md
Keywords: mcp,maven,model-context-protocol,dependency-management
Classifier: Development Status :: 3 - Alpha
Classifier: Programming Language :: Python :: 3
Classifier: Programming Language :: Python :: 3.12
Classifier: License :: OSI Approved :: MIT License
Classifier: Operating System :: OS Independent
Requires-Python: >=3.12
License-File: LICENSE
Requires-Dist: fastmcp>=2.12.4
Requires-Dist: pydantic>=2.11.10
Requires-Dist: requests>=2.32.5
Requires-Dist: httpx>=0.28.1
Requires-Dist: defusedxml>=0.7.1
Provides-Extra: dev
Requires-Dist: pytest; extra == "dev"
Requires-Dist: pytest-cov; extra == "dev"
Requires-Dist: pytest-asyncio; extra == "dev"
Requires-Dist: flake8; extra == "dev"
Requires-Dist: mypy; extra == "dev"
Requires-Dist: black; extra == "dev"
Dynamic: license-file
